pygame_ui/__init__.py
pygame_ui/base.py
pygame_ui/constants.py
pygame_ui/elements.py
pygame_json_ui-1.0.1.0.dist-info/LICENSE
pygame_json_ui-1.0.1.0.dist-info/METADATA
pygame_json_ui-1.0.1.0.dist-info/WHEEL
pygame_json_ui-1.0.1.0.dist-info/top_level.txt
pygame_json_ui-1.0.1.0.dist-info/RECORD
