Metadata-Version: 2.1
Name: pygame-json-ui
Version: 1.0.1.0
Summary: Pygame UI is a package for building user interfaces for pygame in a JSON Format.
Author-email: Xander de Haan <sissydeslang@gmail.com>
Project-URL: Homepage, https://github.com/Rednax-Code/pygame_ui
Project-URL: Bug Tracker, https://github.com/Rednax-Code/pygame_ui/issues
Classifier: Programming Language :: Python :: 3
Classifier: License :: OSI Approved :: MIT License
Classifier: Operating System :: OS Independent
Requires-Python: >=3.10
License-File: LICENSE
Requires-Dist: pygame-ce (>=2.2.1)
